MANIFEST.in
README.md
setup.cfg
setup.py
Pylsy.egg-info/PKG-INFO
Pylsy.egg-info/SOURCES.txt
Pylsy.egg-info/dependency_links.txt
Pylsy.egg-info/requires.txt
Pylsy.egg-info/top_level.txt
pylsy/__init__.py
pylsy/pylsy.py