Metadata-Version: 1.0
Name: Pylsy
Version: 2.71
Summary: Pylsy is a simple library that draws tables in the Terminal.
Home-page: https://github.com/Leviathan1995/Pylsy
Author: leviathan
Author-email: leviathan1995@outlook.com
License: MIT
Platform: UNKNOWN
